{
  "name": "Alesta Midtown",
  "slug": "alesta-midtown",
  "demoNotice": "Demo taslak, resmi site değildir.",
  "location": "Fethiye / Muğla",
  "eyebrow": "Fethiye, Muğla",
  "headline": "Fethiye merkezde apart otel deneyimi için rezervasyon vitrini.",
  "description": "Alesta Midtown için hazırlanan bu taslak; merkezi konumu, apart otel yapısını ve WhatsApp üzerinden hızlı rezervasyon akışını tek sayfada toplar.",
  "type": "Apart Otel",
  "heroImage": "https://www.fethiyetatilkonaklama.com/Uploads/Ilanlar/7aaddc3d-d181-4049-9009-31d994f22347.jpg",
  "featureImage": "https://www.fethiyetatilkonaklama.com/Uploads/IlanResim/fc8d0db1-d544-4b04-9dac-3fc058a4f7e6.jpg",
  "gallery": [
    "https://www.fethiyetatilkonaklama.com/Uploads/Ilanlar/7aaddc3d-d181-4049-9009-31d994f22347.jpg",
    "https://www.fethiyetatilkonaklama.com/Uploads/IlanResim/fc8d0db1-d544-4b04-9dac-3fc058a4f7e6.jpg",
    "https://www.fethiyetatilkonaklama.com/Uploads/IlanResim/66931a02-78b4-4ab6-b994-cf959a6b2e25.jpg",
    "https://www.fethiyetatilkonaklama.com/Uploads/IlanResim/a8eedbe8-557f-45dc-b30e-6fbcea98f96e.jpg"
  ],
  "features": [
    {
      "title": "Merkezi konum vitrini",
      "body": "Fethiye merkez araması yapan misafir için hızlı karar alanı oluşturur."
    },
    {
      "title": "Apart otel anlatımı",
      "body": "Oda, konum ve tesis bilgileri tek sayfada düzenli şekilde sunulur."
    },
    {
      "title": "Doğrudan iletişim",
      "body": "WhatsApp üzerinden aracı olmadan rezervasyon ön talebi alınır."
    }
  ],
  "amenities": [
    {
      "title": "Apart otel",
      "body": "Kısa ve orta süreli konaklama için net kategori."
    },
    {
      "title": "Merkezi Fethiye",
      "body": "Fethiye içi ulaşım ve gezilecek yerlere erişim vurgusu."
    },
    {
      "title": "Galeri",
      "body": "Tesis görselleri karar sürecini hızlandırır."
    },
    {
      "title": "WhatsApp iletişim",
      "body": "Direkt müsaitlik ve rezervasyon sorusu."
    },
    {
      "title": "Mobil uyum",
      "body": "Instagram ve Google trafiği için hızlı sayfa."
    },
    {
      "title": "Direkt ödeme",
      "body": "IBAN veya Iyzico bağlantısı eklenebilir."
    },
    {
      "title": "Komisyonsuz kanal",
      "body": "Platform dışı rezervasyon alternatifi."
    },
    {
      "title": "7 gün yayın",
      "body": "Taslak onaylandıktan sonra canlı siteye dönüştürülür."
    }
  ],
  "contact": {
    "phone": "+90 552 632 35 34",
    "whatsapp": "905526323534",
    "email": "",
    "address": "Fethiye / Muğla",
    "instagram": "alestamidtown"
  },
  "sourceLinks": [
    "https://instagram.com/alestamidtown",
    "https://www.fethiyetatilkonaklama.com/apart-oteler/alesta-midtown-3205"
  ]
}
