{
  "name": "Sapanca Doğa Evleri",
  "slug": "sapanca-doga-evleri",
  "location": "Sapanca",
  "headline": "Yüzyıllık ağaçların gölgesinde, gerçek bir doğa evi deneyimi.",
  "description": "Sapanca Doğa Evleri; sessizliğin hakim olduğu, geniş arazisi içinde müstakil ve şömineli evleriyle size doğanın tam kalbinde bir yaşam sunuyor.",
  "type": "Müstakil Doğa Evi",
  "heroImage": "https://images.pexels.com/photos/2398220/pexels-photo-2398220.jpeg?auto=compress&cs=tinysrgb&w=1260&h=750&dpr=2",
  "featureImage": "https://images.pexels.com/photos/675764/pexels-photo-675764.jpeg?auto=compress&cs=tinysrgb&w=1260&h=750&dpr=2",
  "gallery": [
    "https://images.pexels.com/photos/2398220/pexels-photo-2398220.jpeg?auto=compress&cs=tinysrgb&w=1260&h=750&dpr=2",
    "https://images.pexels.com/photos/675764/pexels-photo-675764.jpeg?auto=compress&cs=tinysrgb&w=1260&h=750&dpr=2",
    "https://images.pexels.com/photos/1061640/pexels-photo-1061640.jpeg?auto=compress&cs=tinysrgb&w=1260&h=750&dpr=2",
    "https://images.pexels.com/photos/2666598/pexels-photo-2666598.jpeg?auto=compress&cs=tinysrgb&w=1260&h=750&dpr=2"
  ],
  "features": [
    {
      "title": "Odun Şöminesi",
      "body": "Kış akşamlarının vazgeçilmezi, çıtırdayan odun ateşi sıcaklığı."
    },
    {
      "title": "Geniş Veranda",
      "body": "Doğa manzarasının tadını çıkarabileceğiniz ferah dış alan."
    },
    {
      "title": "Ev Yapımı Lezzetler",
      "body": "Tesis bünyesinde sunulan yöresel ve doğal ürünlerle kahvaltı."
    }
  ],
  "amenities": [
    { "title": "Şömine", "body": "Isınma ve keyif." },
    { "title": "Otopark", "body": "Tesis bünyesinde." },
    { "title": "WiFi", "body": "Bağlantıda kalın." },
    { "title": "Barbekü", "body": "Dış mekan ızgara." }
  ],
  "contact": {
    "phone": "0532 502 68 61",
    "whatsapp": "905325026861"
  }
}
